matchtune_sdk/MatchTune.py
matchtune_sdk/__init__.py
matchtune_sdk-1.0.1.dist-info/LICENSE.txt
matchtune_sdk-1.0.1.dist-info/METADATA
matchtune_sdk-1.0.1.dist-info/WHEEL
matchtune_sdk-1.0.1.dist-info/top_level.txt
matchtune_sdk-1.0.1.dist-info/RECORD
