Metadata-Version: 2.1
Name: matchtune-sdk
Version: 1.0.1
Summary: A framework library to access MatchTune API
Home-page: https://github.com/matchtune-sdk/python-sdk
Author: Igal Cohen-Hadria
Author-email: igal@matchtune.com
License: UNKNOWN
Keywords: music,matchtune,sdk
Platform: UNKNOWN
Classifier: Programming Language :: Python :: 3
Classifier: License :: OSI Approved :: MIT License
Classifier: Operating System :: OS Independent
